.gitignore
CHANGES.txt
MANIFEST.in
README.txt
setup.py
Products/__init__.py
Products.PloneTestCase.egg-info/PKG-INFO
Products.PloneTestCase.egg-info/SOURCES.txt
Products.PloneTestCase.egg-info/dependency_links.txt
Products.PloneTestCase.egg-info/namespace_packages.txt
Products.PloneTestCase.egg-info/not-zip-safe
Products.PloneTestCase.egg-info/requires.txt
Products.PloneTestCase.egg-info/top_level.txt
Products/PloneTestCase/PloneTestCase.py
Products/PloneTestCase/VERSION.txt
Products/PloneTestCase/__init__.py
Products/PloneTestCase/five.py
Products/PloneTestCase/framework.py
Products/PloneTestCase/interfaces.py
Products/PloneTestCase/layer.py
Products/PloneTestCase/ptc.py
Products/PloneTestCase/runalltests.py
Products/PloneTestCase/setup.py
Products/PloneTestCase/testDocument.py
Products/PloneTestCase/testInterfaces.py
Products/PloneTestCase/testMembershipTool.py
Products/PloneTestCase/testMemoize.py
Products/PloneTestCase/testPloneTestCase.py
Products/PloneTestCase/testSkeleton.py
Products/PloneTestCase/tests.py
Products/PloneTestCase/utils.py
Products/PloneTestCase/version.py