Metadata-Version: 1.0
Name: Products.PloneTestCase
Version: 0.9.17
Summary: Integration testing framework for Plone.
Home-page: http://plone.org/products/plonetestcase
Author: Stefan H. Holek
Author-email: stefan@epy.co.at
License: GPL
Keywords: plone testing
Platform: UNKNOWN
Classifier: Framework :: Plone
Classifier: Framework :: Zope2
Classifier: Programming Language :: Python
Classifier: Topic :: Software Development :: Libraries :: Python Modules
